odoo/addons/fieldservice_stage_validation/README.rst
odoo/addons/fieldservice_stage_validation/__init__.py
odoo/addons/fieldservice_stage_validation/__manifest__.py
odoo/addons/fieldservice_stage_validation/i18n/es.po
odoo/addons/fieldservice_stage_validation/i18n/es_AR.po
odoo/addons/fieldservice_stage_validation/i18n/fieldservice_stage_validation.pot
odoo/addons/fieldservice_stage_validation/i18n/fr_FR.po
odoo/addons/fieldservice_stage_validation/i18n/it.po
odoo/addons/fieldservice_stage_validation/i18n/pt_BR.po
odoo/addons/fieldservice_stage_validation/i18n/pt_PT.po
odoo/addons/fieldservice_stage_validation/i18n/tr.po
odoo/addons/fieldservice_stage_validation/models/__init__.py
odoo/addons/fieldservice_stage_validation/models/fsm_equipment.py
odoo/addons/fieldservice_stage_validation/models/fsm_location.py
odoo/addons/fieldservice_stage_validation/models/fsm_order.py
odoo/addons/fieldservice_stage_validation/models/fsm_person.py
odoo/addons/fieldservice_stage_validation/models/fsm_stage.py
odoo/addons/fieldservice_stage_validation/models/validate_utils.py
odoo/addons/fieldservice_stage_validation/readme/CONFIGURE.md
odoo/addons/fieldservice_stage_validation/readme/CONTRIBUTORS.md
odoo/addons/fieldservice_stage_validation/readme/DESCRIPTION.md
odoo/addons/fieldservice_stage_validation/readme/ROADMAP.md
odoo/addons/fieldservice_stage_validation/readme/USAGE.md
odoo/addons/fieldservice_stage_validation/security/ir.model.access.csv
odoo/addons/fieldservice_stage_validation/static/description/icon.png
odoo/addons/fieldservice_stage_validation/static/description/index.html
odoo/addons/fieldservice_stage_validation/tests/__init__.py
odoo/addons/fieldservice_stage_validation/tests/test_fsm_stage_validation.py
odoo/addons/fieldservice_stage_validation/views/fsm_stage.xml
odoo_addon_fieldservice_stage_validation-17.0.1.1.0.dist-info/METADATA
odoo_addon_fieldservice_stage_validation-17.0.1.1.0.dist-info/WHEEL
odoo_addon_fieldservice_stage_validation-17.0.1.1.0.dist-info/top_level.txt
odoo_addon_fieldservice_stage_validation-17.0.1.1.0.dist-info/RECORD
